neuroHarmonize/__init__.py
neuroHarmonize/harmonizationApply.py
neuroHarmonize/harmonizationLearn.py
neuroHarmonize/harmonizationNIFTI.py
neuroHarmonize-2.4.5.dist-info/LICENSE
neuroHarmonize-2.4.5.dist-info/METADATA
neuroHarmonize-2.4.5.dist-info/WHEEL
neuroHarmonize-2.4.5.dist-info/top_level.txt
neuroHarmonize-2.4.5.dist-info/RECORD
