Metadata-Version: 2.1
Name: neuroHarmonize
Version: 2.4.5
Summary: Harmonization tools for multi-center neuroimaging studies.
Home-page: https://github.com/rpomponio/neuroHarmonize
Author: Raymond Pomponio
Author-email: raymond.pomponio@outlook.com
Project-URL: Bug Tracker, https://github.com/rpomponio/neuroHarmonize/issues
Classifier: Programming Language :: Python :: 3
Classifier: License :: OSI Approved :: MIT License
Classifier: Operating System :: OS Independent
Requires-Python: >=3.6
License-File: LICENSE
